causaldag/__init__.py
causaldag/loaders.py
causaldag/datasets/__init__.py
causaldag/datasets/networks.py
profiling/__init__.py
profiling/compare_all_dags.py
profiling/profile_cpdag.py
profiling/profile_gsp.py
profiling/profile_hsic.py
profiling/profile_igsp.py
profiling/profile_init.py
profiling/profile_pc.py
profiling/profile_perm2dag.py
profiling/time_create_graph.py
profiling/time_dec.py
tests/test_classes/__init__.py
tests/test_classes/test_ancestral_graph.py
tests/test_classes/test_dag.py
tests/test_classes/test_dag_basics.py
tests/test_classes/test_pdag.py
tests/test_structure_learning/__init__.py
tests/test_structure_learning/test_gsp.py
tests/test_structure_learning/test_pcalg.py
causaldag-0.1a163.dist-info/LICENSE.txt
causaldag-0.1a163.dist-info/METADATA
causaldag-0.1a163.dist-info/WHEEL
causaldag-0.1a163.dist-info/top_level.txt
causaldag-0.1a163.dist-info/RECORD
